typeshed_client/__init__.py
typeshed_client/finder.py
typeshed_client/parser.py
typeshed_client/py.typed
typeshed_client/resolver.py
typeshed_client/typeshed/VERSIONS
typeshed_client/typeshed/__future__.pyi
typeshed_client/typeshed/__main__.pyi
typeshed_client/typeshed/_ast.pyi
typeshed_client/typeshed/_bisect.pyi
typeshed_client/typeshed/_bootlocale.pyi
typeshed_client/typeshed/_codecs.pyi
typeshed_client/typeshed/_collections_abc.pyi
typeshed_client/typeshed/_compat_pickle.pyi
typeshed_client/typeshed/_compression.pyi
typeshed_client/typeshed/_csv.pyi
typeshed_client/typeshed/_ctypes.pyi
typeshed_client/typeshed/_curses.pyi
typeshed_client/typeshed/_decimal.pyi
typeshed_client/typeshed/_dummy_thread.pyi
typeshed_client/typeshed/_dummy_threading.pyi
typeshed_client/typeshed/_heapq.pyi
typeshed_client/typeshed/_imp.pyi
typeshed_client/typeshed/_interpchannels.pyi
typeshed_client/typeshed/_interpqueues.pyi
typeshed_client/typeshed/_interpreters.pyi
typeshed_client/typeshed/_json.pyi
typeshed_client/typeshed/_locale.pyi
typeshed_client/typeshed/_lsprof.pyi
typeshed_client/typeshed/_markupbase.pyi
typeshed_client/typeshed/_msi.pyi
typeshed_client/typeshed/_operator.pyi
typeshed_client/typeshed/_osx_support.pyi
typeshed_client/typeshed/_posixsubprocess.pyi
typeshed_client/typeshed/_py_abc.pyi
typeshed_client/typeshed/_pydecimal.pyi
typeshed_client/typeshed/_random.pyi
typeshed_client/typeshed/_sitebuiltins.pyi
typeshed_client/typeshed/_socket.pyi
typeshed_client/typeshed/_stat.pyi
typeshed_client/typeshed/_thread.pyi
typeshed_client/typeshed/_threading_local.pyi
typeshed_client/typeshed/_tkinter.pyi
typeshed_client/typeshed/_tracemalloc.pyi
typeshed_client/typeshed/_warnings.pyi
typeshed_client/typeshed/_weakref.pyi
typeshed_client/typeshed/_weakrefset.pyi
typeshed_client/typeshed/_winapi.pyi
typeshed_client/typeshed/abc.pyi
typeshed_client/typeshed/aifc.pyi
typeshed_client/typeshed/antigravity.pyi
typeshed_client/typeshed/argparse.pyi
typeshed_client-2.7.0.dist-info/LICENSE
typeshed_client-2.7.0.dist-info/METADATA
typeshed_client-2.7.0.dist-info/WHEEL
typeshed_client-2.7.0.dist-info/top_level.txt
typeshed_client-2.7.0.dist-info/RECORD
