Metadata-Version: 2.1
Name: typeshed_client
Version: 2.7.0
Summary: A library for accessing stubs in typeshed.
Home-page: https://github.com/JelleZijlstra/typeshed_client
Author: Jelle Zijlstra
Author-email: jelle.zijlstra@gmail.com
License: MIT
Project-URL: Bug Tracker, https://github.com/JelleZijlstra/typeshed_client/issues
Keywords: typeshed typing annotations
Classifier: Development Status :: 3 - Alpha
Classifier: Environment :: Console
Classifier: Intended Audience :: Developers
Classifier: License :: OSI Approved :: MIT License
Classifier: Operating System :: OS Independent
Classifier: Programming Language :: Python
Classifier: Programming Language :: Python :: 3.8
Classifier: Programming Language :: Python :: 3.9
Classifier: Programming Language :: Python :: 3.10
Classifier: Programming Language :: Python :: 3.11
Classifier: Programming Language :: Python :: 3.12
Classifier: Programming Language :: Python :: 3.13
Classifier: Topic :: Software Development
Requires-Python: >=3.8
License-File: LICENSE
Requires-Dist: importlib_resources>=1.4.0
Requires-Dist: typing-extensions>=4.5.0
